tglfnn_ukaea/__init__.py
tglfnn_ukaea/loader.py
tglfnn_ukaea/weights/multimachine.pkl
tglfnn_ukaea-0.1.0.dist-info/licenses/LICENSE
tglfnn_ukaea-0.1.0.dist-info/METADATA
tglfnn_ukaea-0.1.0.dist-info/WHEEL
tglfnn_ukaea-0.1.0.dist-info/top_level.txt
tglfnn_ukaea-0.1.0.dist-info/RECORD
