Metadata-Version: 2.4
Name: tglfnn_ukaea
Version: 0.1.0
Summary: Neural network surrogate of TGLF (weights only)
Author: UKAEA
License-Expression: LGPL-3.0
Project-URL: Homepage, https://github.com/ukaea/tglfnn-ukaea/
Project-URL: Repository, https://github.com/ukaea/tglfnn-ukaea/
Requires-Python: >=3
License-File: LICENSE
Requires-Dist: numpy>2
Dynamic: license-file
